{
  "b": 209,
  "disableInputWhenNotFocused": true,
  "mangledName": "secret_32leveljm",
  "name": "secret leveljm",
  "r": 209,
  "standardSortMethod": true,
  "stopSoundsOnStartup": true,
  "title": "",
  "v": 209,
  "uiSettings": {
    "grid": false,
    "gridType": "rectangular",
    "gridWidth": 32,
    "gridHeight": 32,
    "gridOffsetX": 0,
    "gridOffsetY": 0,
    "gridColor": 10401023,
    "gridAlpha": 0.8,
    "snap": false,
    "zoomFactor": 0.5653158055126317,
    "windowMask": false
  },
  "objectsGroups": [],
  "variables": [],
  "instances": [
    {
      "angle": 0,
      "customSize": true,
      "depth": 1,
      "height": 6233,
      "layer": "",
      "name": "YellowBackground",
      "persistentUuid": "a631efa1-d149-4429-a0ac-5cb6ca489655",
      "width": 39234,
      "x": -13095,
      "y": -2563,
      "zOrder": 1,
      "numberProperties": [],
      "stringProperties": [],
      "initialVariables": []
    },
    {
      "angle": 0,
      "customSize": false,
      "height": 0,
      "layer": "",
      "name": "SmallPlatform",
      "persistentUuid": "133fa539-5859-47ff-9702-1907e401fd80",
      "width": 0,
      "x": -1,
      "y": 634,
      "zOrder": 2,
      "numberProperties": [],
      "stringProperties": [],
      "initialVariables": []
    },
    {
      "angle": 0,
      "customSize": false,
      "height": 0,
      "layer": "",
      "name": "SmallPlatform",
      "persistentUuid": "ef1b9b41-e0fb-4ef3-811b-fbc12aaea4d2",
      "width": 0,
      "x": 140,
      "y": 634,
      "zOrder": 3,
      "numberProperties": [],
      "stringProperties": [],
      "initialVariables": []
    },
    {
      "angle": 0,
      "customSize": true,
      "depth": 1,
      "height": 120,
      "layer": "",
      "name": "DinoVita",
      "persistentUuid": "c8269fba-6fb2-49b5-99d5-87ebdd782de0",
      "width": 119,
      "x": -1,
      "y": 528,
      "zOrder": 100,
      "numberProperties": [],
      "stringProperties": [],
      "initialVariables": []
    },
    {
      "angle": 0,
      "customSize": false,
      "height": 0,
      "layer": "",
      "name": "IndustrialBlock4",
      "persistentUuid": "bdd6211b-5dd7-4821-a55f-fdf4718909e2",
      "width": 0,
      "x": 280,
      "y": 574,
      "zOrder": 5,
      "numberProperties": [],
      "stringProperties": [],
      "initialVariables": []
    },
    {
      "angle": 0,
      "customSize": false,
      "height": 0,
      "layer": "",
      "name": "IndustrialPlatform2",
      "persistentUuid": "e925fe81-e64d-4a32-9943-7d12d2e3a881",
      "width": 0,
      "x": 422,
      "y": 629,
      "zOrder": 6,
      "numberProperties": [],
      "stringProperties": [],
      "initialVariables": []
    },
    {
      "angle": 0,
      "customSize": false,
      "height": 0,
      "layer": "",
      "name": "IndustrialPlatform",
      "persistentUuid": "21ed8512-7117-4cb7-bc59-c5bba29e7c6a",
      "width": 0,
      "x": 563,
      "y": 629,
      "zOrder": 7,
      "numberProperties": [],
      "stringProperties": [],
      "initialVariables": []
    },
    {
      "angle": 0,
      "customSize": false,
      "height": 0,
      "layer": "",
      "name": "IndustrialPlatform",
      "persistentUuid": "d170eb9c-1fd2-4c4e-97fb-b0e4b4493c8e",
      "width": 0,
      "x": 705,
      "y": 629,
      "zOrder": 8,
      "numberProperties": [],
      "stringProperties": [],
      "initialVariables": []
    },
    {
      "angle": 0,
      "customSize": false,
      "height": 0,
      "layer": "",
      "name": "IndustrialBlock4",
      "persistentUuid": "53184749-7a1b-4a6b-8330-41d744c9bde2",
      "width": 0,
      "x": 844,
      "y": 629,
      "zOrder": 9,
      "numberProperties": [],
      "stringProperties": [],
      "initialVariables": []
    },
    {
      "angle": 0,
      "customSize": false,
      "height": 0,
      "layer": "",
      "name": "IndustrialBlock4",
      "persistentUuid": "7db3de50-aeb2-4616-9002-98cd922b250f",
      "width": 0,
      "x": 986,
      "y": 629,
      "zOrder": 10,
      "numberProperties": [],
      "stringProperties": [],
      "initialVariables": []
    },
    {
      "angle": 0,
      "customSize": false,
      "height": 0,
      "layer": "",
      "name": "IndustrialBlock4",
      "persistentUuid": "3265b270-71dc-4def-9709-32827d61c8c7",
      "width": 0,
      "x": 849,
      "y": 489,
      "zOrder": 11,
      "numberProperties": [],
      "stringProperties": [],
      "initialVariables": []
    },
    {
      "angle": 0,
      "customSize": false,
      "height": 0,
      "layer": "",
      "name": "IndustrialBlock4",
      "persistentUuid": "48ba767b-3bc3-4704-8d93-a4796c4326f3",
      "width": 0,
      "x": 988,
      "y": 489,
      "zOrder": 12,
      "numberProperties": [],
      "stringProperties": [],
      "initialVariables": []
    },
    {
      "angle": 0,
      "customSize": false,
      "height": 0,
      "layer": "",
      "name": "IndustrialBlock4",
      "persistentUuid": "731d1740-747a-4788-b032-5f51ca000965",
      "width": 0,
      "x": 1130,
      "y": 629,
      "zOrder": 13,
      "numberProperties": [],
      "stringProperties": [],
      "initialVariables": []
    },
    {
      "angle": 0,
      "customSize": false,
      "height": 0,
      "layer": "",
      "name": "IndustrialBlock4",
      "persistentUuid": "e63c1de0-f31c-410c-93f4-f80dbc3d8b84",
      "width": 0,
      "x": 1275,
      "y": 629,
      "zOrder": 14,
      "numberProperties": [],
      "stringProperties": [],
      "initialVariables": []
    },
    {
      "angle": 0,
      "customSize": false,
      "height": 0,
      "layer": "",
      "name": "IndustrialPlatform",
      "persistentUuid": "761279b7-59aa-467d-b361-661e7cd2c542",
      "width": 0,
      "x": 1416,
      "y": 629,
      "zOrder": 15,
      "numberProperties": [],
      "stringProperties": [],
      "initialVariables": []
    },
    {
      "angle": 0,
      "customSize": true,
      "depth": 1,
      "height": 116,
      "layer": "",
      "name": "eggsJm3",
      "persistentUuid": "1afa4c1f-3dfd-41b2-8667-2868dab19905",
      "width": 201,
      "x": 290,
      "y": 482,
      "zOrder": 16,
      "numberProperties": [],
      "stringProperties": [],
      "initialVariables": []
    },
    {
      "angle": 0,
      "customSize": true,
      "depth": 1,
      "height": 99,
      "layer": "",
      "name": "eggsJm3",
      "persistentUuid": "22f1d5df-2cd5-4116-b105-2457fc279d60",
      "width": 183,
      "x": 1143,
      "y": 542,
      "zOrder": 17,
      "numberProperties": [],
      "stringProperties": [],
      "initialVariables": []
    },
    {
      "angle": 0,
      "customSize": true,
      "depth": 1,
      "height": 140,
      "layer": "",
      "name": "IndustrialPlatform2",
      "persistentUuid": "22a855c0-fe98-409d-9ec2-18df7f872657",
      "width": 1838,
      "x": 1553,
      "y": 629,
      "zOrder": 18,
      "numberProperties": [],
      "stringProperties": [],
      "initialVariables": []
    },
    {
      "angle": 0,
      "customSize": false,
      "height": 0,
      "layer": "",
      "name": "YellowButtonOnSocle",
      "persistentUuid": "5ffd85ec-0452-4d40-9003-1d56a0755147",
      "width": 0,
      "x": 1586,
      "y": 489,
      "zOrder": 19,
      "numberProperties": [],
      "stringProperties": [],
      "initialVariables": []
    },
    {
      "angle": 0,
      "customSize": false,
      "height": 0,
      "layer": "",
      "name": "Monitor",
      "persistentUuid": "7b4de594-4acc-4396-a12d-fd224e13f011",
      "width": 0,
      "x": 1589,
      "y": 436,
      "zOrder": 20,
      "numberProperties": [],
      "stringProperties": [],
      "initialVariables": []
    },
    {
      "angle": 0,
      "customSize": true,
      "depth": 1,
      "height": 511,
      "layer": "",
      "name": "GreenBlock",
      "persistentUuid": "62d29859-a431-454e-9f5e-3eebde57f594",
      "width": 315,
      "x": 1747,
      "y": 115,
      "zOrder": 21,
      "numberProperties": [],
      "stringProperties": [],
      "initialVariables": []
    },
    {
      "angle": 0,
      "customSize": true,
      "depth": 1,
      "height": 128,
      "layer": "",
      "name": "SecurityFence",
      "persistentUuid": "9ca5ca17-5dbb-44a2-b8f0-275922837ff1",
      "width": 319,
      "x": 1742,
      "y": 473,
      "zOrder": 22,
      "numberProperties": [],
      "stringProperties": [],
      "initialVariables": []
    },
    {
      "angle": 0,
      "customSize": false,
      "height": 0,
      "layer": "",
      "name": "IndustrialPlatform2",
      "persistentUuid": "498bca86-2953-49c3-94ea-679e2b525031",
      "width": 0,
      "x": 2094,
      "y": 491,
      "zOrder": 23,
      "numberProperties": [],
      "stringProperties": [],
      "initialVariables": []
    },
    {
      "angle": 0,
      "customSize": false,
      "height": 0,
      "layer": "",
      "name": "IndustrialBlock4",
      "persistentUuid": "85c1261c-ed25-4271-9e69-237fbc112594",
      "width": 0,
      "x": 2231,
      "y": 494,
      "zOrder": 24,
      "numberProperties": [],
      "stringProperties": [],
      "initialVariables": []
    },
    {
      "angle": 0,
      "customSize": false,
      "height": 0,
      "layer": "",
      "name": "IndustrialBlock4",
      "persistentUuid": "11148ca4-a7ec-4edf-b34b-150de5486b71",
      "width": 0,
      "x": 2231,
      "y": 356,
      "zOrder": 25,
      "numberProperties": [],
      "stringProperties": [],
      "initialVariables": []
    },
    {
      "angle": 0,
      "customSize": false,
      "height": 0,
      "layer": "",
      "name": "IndustrialBlock4",
      "persistentUuid": "59dc804d-7983-459a-b4ae-338d01572293",
      "width": 0,
      "x": 2369,
      "y": 492,
      "zOrder": 26,
      "numberProperties": [],
      "stringProperties": [],
      "initialVariables": []
    },
    {
      "angle": 0,
      "customSize": false,
      "height": 0,
      "layer": "",
      "name": "IndustrialBlock4",
      "persistentUuid": "8b71463c-d1ab-4f7c-a79f-14860581c249",
      "width": 0,
      "x": 2367,
      "y": 356,
      "zOrder": 27,
      "numberProperties": [],
      "stringProperties": [],
      "initialVariables": []
    },
    {
      "angle": 0,
      "customSize": false,
      "height": 0,
      "layer": "",
      "name": "IndustrialBlock4",
      "persistentUuid": "7e58f90d-7901-4123-b234-14aaa7468fa0",
      "width": 0,
      "x": 2370,
      "y": 216,
      "zOrder": 28,
      "numberProperties": [],
      "stringProperties": [],
      "initialVariables": []
    },
    {
      "angle": 0,
      "customSize": false,
      "height": 0,
      "layer": "",
      "name": "IndustrialBlock4",
      "persistentUuid": "42f9fd75-3365-4a0a-a0f6-2e867b24bdad",
      "width": 0,
      "x": 2510,
      "y": 500,
      "zOrder": 29,
      "numberProperties": [],
      "stringProperties": [],
      "initialVariables": []
    },
    {
      "angle": 0,
      "customSize": false,
      "height": 0,
      "layer": "",
      "name": "IndustrialBlock4",
      "persistentUuid": "9f31e3af-9aee-401f-837b-ba4568dfea72",
      "width": 0,
      "x": 2507,
      "y": 363,
      "zOrder": 30,
      "numberProperties": [],
      "stringProperties": [],
      "initialVariables": []
    },
    {
      "angle": 0,
      "customSize": false,
      "height": 0,
      "layer": "",
      "name": "IndustrialBlock4",
      "persistentUuid": "48828176-b513-4a0f-8801-9749aa071ec0",
      "width": 0,
      "x": 2650,
      "y": 503,
      "zOrder": 31,
      "numberProperties": [],
      "stringProperties": [],
      "initialVariables": []
    },
    {
      "angle": 0,
      "customSize": true,
      "depth": 1,
      "height": 140,
      "layer": "",
      "name": "IndustrialPlatform2",
      "persistentUuid": "0605d529-835a-473a-b3eb-6c500af4e046",
      "width": 2097,
      "x": 3391,
      "y": 629,
      "zOrder": 101,
      "numberProperties": [],
      "stringProperties": [],
      "initialVariables": []
    }
  ],
  "objects": [
    {
      "assetStoreId": "2a16fd749b7fb56b85e1152a4f7d7d5de507cef1d8888320a770ea0f63a2edd2",
      "height": 128,
      "name": "YellowBackground",
      "texture": "tiled_Yellow background.png",
      "type": "TiledSpriteObject::TiledSprite",
      "width": 128,
      "variables": [],
      "effects": [],
      "behaviors": []
    },
    {
      "adaptCollisionMaskAutomatically": true,
      "assetStoreId": "1f1fbc1287e2e4236dbe4c40deff5d7665e60ee41b30dc403a0d0bb3b867756f",
      "name": "WideRectangleGlass",
      "type": "Sprite",
      "updateIfNotVisible": false,
      "variables": [],
      "effects": [],
      "behaviors": [],
      "animations": [
        {
          "name": "Broken",
          "useMultipleDirections": false,
          "directions": [
            {
              "looping": true,
              "timeBetweenFrames": 0.025,
              "sprites": [
                {
                  "hasCustomCollisionMask": true,
                  "image": "Wide rectangle glass_Broken.png",
                  "points": [],
                  "originPoint": {
                    "name": "origine",
                    "x": 0,
                    "y": 0
                  },
                  "centerPoint": {
                    "automatic": true,
                    "name": "centre",
                    "x": 0,
                    "y": 0
                  },
                  "customCollisionMask": [
                    [
                      {
                        "x": 0,
                        "y": 0
                      },
                      {
                        "x": 140,
                        "y": 0
                      },
                      {
                        "x": 140,
                        "y": 220
                      },
                      {
                        "x": 0,
                        "y": 220
                      }
                    ]
                  ]
                }
              ]
            }
          ]
        },
        {
          "name": "Damaged",
          "useMultipleDirections": false,
          "directions": [
            {
              "looping": true,
              "timeBetweenFrames": 0.025,
              "sprites": [
                {
                  "hasCustomCollisionMask": true,
                  "image": "Wide rectangle glass_Damaged.png",
                  "points": [],
                  "originPoint": {
                    "name": "origine",
                    "x": 0,
                    "y": 0
                  },
                  "centerPoint": {
                    "automatic": true,
                    "name": "centre",
                    "x": 0,
                    "y": 0
                  },
                  "customCollisionMask": [
                    [
                      {
                        "x": 0,
                        "y": 0
                      },
                      {
                        "x": 140,
                        "y": 0
                      },
                      {
                        "x": 140,
                        "y": 220
                      },
                      {
                        "x": 0,
                        "y": 220
                      }
                    ]
                  ]
                }
              ]
            }
          ]
        },
        {
          "name": "Perfect",
          "useMultipleDirections": false,
          "directions": [
            {
              "looping": true,
              "timeBetweenFrames": 0.025,
              "sprites": [
                {
                  "hasCustomCollisionMask": true,
                  "image": "Wide rectangle glass_Perfect.png",
                  "points": [],
                  "originPoint": {
                    "name": "origine",
                    "x": 0,
                    "y": 0
                  },
                  "centerPoint": {
                    "automatic": true,
                    "name": "centre",
                    "x": 0,
                    "y": 0
                  },
                  "customCollisionMask": [
                    [
                      {
                        "x": 0,
                        "y": 0
                      },
                      {
                        "x": 140,
                        "y": 0
                      },
                      {
                        "x": 140,
                        "y": 220
                      },
                      {
                        "x": 0,
                        "y": 220
                      }
                    ]
                  ]
                }
              ]
            }
          ]
        }
      ]
    }
  ],
  "objectsFolderStructure": {
    "folderName": "__ROOT",
    "children": [
      {
        "objectName": "YellowBackground"
      },
      {
        "objectName": "WideRectangleGlass"
      }
    ]
  },
  "events": [
    {
      "type": "BuiltinCommonInstructions::Standard",
      "conditions": [],
      "actions": []
    },
    {
      "type": "BuiltinCommonInstructions::Link",
      "include": {
        "includeConfig": 0
      },
      "target": "Intojm"
    },
    {
      "type": "BuiltinCommonInstructions::Standard",
      "conditions": [
        {
          "type": {
            "value": "Vitesse"
          },
          "parameters": [
            "DinoVita",
            "=",
            "0"
          ]
        }
      ],
      "actions": [
        {
          "type": {
            "value": "AnimatableCapability::AnimatableBehavior::SetName"
          },
          "parameters": [
            "DinoVita",
            "Animation",
            "=",
            "\"Idle\""
          ]
        }
      ]
    },
    {
      "type": "BuiltinCommonInstructions::Standard",
      "conditions": [],
      "actions": []
    },
    {
      "type": "BuiltinCommonInstructions::Standard",
      "conditions": [
        {
          "type": {
            "value": "PlatformBehavior::PlatformerObjectBehavior::IsMovingEvenALittle"
          },
          "parameters": [
            "DinoVita",
            "PlatformerObject"
          ]
        }
      ],
      "actions": [
        {
          "type": {
            "value": "AnimatableCapability::AnimatableBehavior::SetName"
          },
          "parameters": [
            "DinoVita",
            "Animation",
            "=",
            "\"Move\""
          ]
        }
      ]
    },
    {
      "type": "BuiltinCommonInstructions::Standard",
      "conditions": [
        {
          "type": {
            "value": "PlatformBehavior::PlatformerObjectBehavior::IsUsingControl"
          },
          "parameters": [
            "DinoVita",
            "PlatformerObject",
            "\"Down\""
          ]
        }
      ],
      "actions": [
        {
          "type": {
            "value": "AnimatableCapability::AnimatableBehavior::SetName"
          },
          "parameters": [
            "DinoVita",
            "Animation",
            "=",
            "\"Crouch\""
          ]
        }
      ]
    },
    {
      "type": "BuiltinCommonInstructions::Standard",
      "conditions": [
        {
          "type": {
            "value": "KeyPressed"
          },
          "parameters": [
            "",
            "Right"
          ]
        }
      ],
      "actions": [
        {
          "type": {
            "value": "FlippableCapability::FlippableBehavior::FlipX"
          },
          "parameters": [
            "DinoVita",
            "Flippable",
            ""
          ]
        }
      ]
    },
    {
      "type": "BuiltinCommonInstructions::Standard",
      "conditions": [
        {
          "type": {
            "value": "KeyPressed"
          },
          "parameters": [
            "",
            "Left"
          ]
        }
      ],
      "actions": [
        {
          "type": {
            "value": "FlippableCapability::FlippableBehavior::FlipX"
          },
          "parameters": [
            "DinoVita",
            "Flippable",
            "yes"
          ]
        }
      ]
    }
  ],
  "layers": [
    {
      "ambientLightColorB": 200,
      "ambientLightColorG": 200,
      "ambientLightColorR": 200,
      "camera3DFarPlaneDistance": 10000,
      "camera3DFieldOfView": 45,
      "camera3DNearPlaneDistance": 3,
      "cameraType": "",
      "followBaseLayerCamera": false,
      "isLightingLayer": false,
      "isLocked": false,
      "name": "",
      "renderingType": "",
      "visibility": true,
      "cameras": [
        {
          "defaultSize": true,
          "defaultViewport": true,
          "height": 0,
          "viewportBottom": 1,
          "viewportLeft": 0,
          "viewportRight": 1,
          "viewportTop": 0,
          "width": 0
        }
      ],
      "effects": [
        {
          "effectType": "Scene3D::HemisphereLight",
          "name": "3D Light",
          "doubleParameters": {
            "elevation": 45,
            "intensity": 1,
            "rotation": 0
          },
          "stringParameters": {
            "groundColor": "64;64;64",
            "skyColor": "255;255;255",
            "top": "Y-"
          },
          "booleanParameters": {}
        }
      ]
    }
  ],
  "behaviorsSharedData": [
    {
      "name": "Animation",
      "type": "AnimatableCapability::AnimatableBehavior"
    },
    {
      "name": "Effect",
      "type": "EffectCapability::EffectBehavior"
    },
    {
      "name": "Flippable",
      "type": "FlippableCapability::FlippableBehavior"
    },
    {
      "name": "Opacity",
      "type": "OpacityCapability::OpacityBehavior"
    },
    {
      "name": "Platform",
      "type": "PlatformBehavior::PlatformBehavior"
    },
    {
      "name": "PlatformerObject",
      "type": "PlatformBehavior::PlatformerObjectBehavior"
    },
    {
      "name": "Resizable",
      "type": "ResizableCapability::ResizableBehavior"
    },
    {
      "name": "Scale",
      "type": "ScalableCapability::ScalableBehavior"
    },
    {
      "name": "SmoothCamera",
      "type": "SmoothCamera::SmoothCamera"
    },
    {
      "name": "SmoothPlatformerCamera",
      "type": "SmoothCamera::SmoothPlatformerCamera"
    }
  ]
}